{
  "CATANO": [
    {
      "zone": "Bo. Palmas",
      "area": "CATANO"
    }
  ],
  "CAROLINA": [
    {
      "zone": "Ave. 65 Infanteria",
      "area": "CAROLINA"
    },
    {
      "zone": "Bo. Buena Vista",
      "area": "CAROLINA"
    },
    {
      "zone": "Bo. Canovanillas",
      "area": "CAROLINA"
    },
    {
      "zone": "Bo. Santa Cruz",
      "area": "CAROLINA"
    },
    {
      "zone": "CANOVANILLAS",
      "area": "CAROLINA"
    },
    {
      "zone": "COND ROBERTO CLEMENTE APARTMENTS",
      "area": "CAROLINA"
    },
    {
      "zone": "JARD DE COUNTRY CLUB   B",
      "area": "CAROLINA"
    },
    {
      "zone": "MANSIONES DE CAROLINA",
      "area": "CAROLINA"
    },
    {
      "zone": "SABANA ABAJO",
      "area": "CAROLINA"
    },
    {
      "zone": "URB COUNTRY CLUB",
      "area": "CAROLINA"
    },
    {
      "zone": "URB SABANA GARDENS",
      "area": "CAROLINA"
    },
    {
      "zone": "URB VILLA CAROLINA",
      "area": "CAROLINA"
    },
    {
      "zone": "Urb. Ext. El Comandant",
      "area": "CAROLINA"
    },
    {
      "zone": "Urb. Metropolis",
      "area": "CAROLINA"
    }
  ],
  "TRUJILLO ALTO": [
    {
      "zone": "BO QUEBRADA GRANDE",
      "area": "TRUJILLO ALTO"
    },
    {
      "zone": "Bo. Carraizo",
      "area": "TRUJILLO ALTO"
    },
    {
      "zone": "QDA NEGRITO VALLE BUENOS AIRES",
      "area": "TRUJILLO ALTO"
    },
    {
      "zone": "Urb. Haciendas Carraizo",
      "area": "TRUJILLO ALTO"
    }
  ],
  "GUAYNABO": [
    {
      "zone": "BO SANTA ROSA",
      "area": "GUAYNABO"
    },
    {
      "zone": "BO SANTA ROSA III/LOS CRUZ",
      "area": "GUAYNABO"
    }
  ],
  "SAN JUAN": [
    {
      "zone": "Ave. 65 De Infanteria",
      "area": "SAN JUAN"
    },
    {
      "zone": "Ave. Munoz RIvera",
      "area": "SAN JUAN"
    },
    {
      "zone": "Ave. Pinero",
      "area": "SAN JUAN"
    },
    {
      "zone": "Ave. Roosevelt",
      "area": "SAN JUAN"
    },
    {
      "zone": "BO OBRERO",
      "area": "SAN JUAN"
    },
    {
      "zone": "BO SABANA LLANA PARC FALU",
      "area": "SAN JUAN"
    },
    {
      "zone": "Bo. Hill Brothers",
      "area": "SAN JUAN"
    },
    {
      "zone": "Bo. Obrero",
      "area": "SAN JUAN"
    },
    {
      "zone": "COND EL CADIZ",
      "area": "SAN JUAN"
    },
    {
      "zone": "COND PAOLA",
      "area": "SAN JUAN"
    },
    {
      "zone": "COND PARQUE CENTRAL",
      "area": "SAN JUAN"
    },
    {
      "zone": "COND VEREDAS DEL MONTE P3",
      "area": "SAN JUAN"
    },
    {
      "zone": "CONDOMINIO ESCORIAL ALTOS",
      "area": "SAN JUAN"
    },
    {
      "zone": "CUPEY",
      "area": "SAN JUAN"
    },
    {
      "zone": "GOBERNADOR PIÑERO",
      "area": "SAN JUAN"
    },
    {
      "zone": "HATO REY NORTE",
      "area": "SAN JUAN"
    },
    {
      "zone": "REPARAR BASE MUELA DESPEGADA",
      "area": "SAN JUAN"
    },
    {
      "zone": "Res. Las Margaritas S",
      "area": "SAN JUAN"
    },
    {
      "zone": "Res. San Martin",
      "area": "SAN JUAN"
    },
    {
      "zone": "Res. Vista Hermosa",
      "area": "SAN JUAN"
    },
    {
      "zone": "SABANA LLANA NORTE",
      "area": "SAN JUAN"
    },
    {
      "zone": "Sector San José",
      "area": "SAN JUAN"
    },
    {
      "zone": "URB CAPARRA TERRACE",
      "area": "SAN JUAN"
    },
    {
      "zone": "URB COUNTRY CLUB",
      "area": "SAN JUAN"
    },
    {
      "zone": "URB LA RIVIERA",
      "area": "SAN JUAN"
    },
    {
      "zone": "URB LAS LOMAS",
      "area": "SAN JUAN"
    },
    {
      "zone": "URB RPTO METROPOLITANO",
      "area": "SAN JUAN"
    },
    {
      "zone": "URB SAN MARTIN",
      "area": "SAN JUAN"
    },
    {
      "zone": "Urb. Club Manor",
      "area": "SAN JUAN"
    },
    {
      "zone": "Urb. Country Club 1 Se",
      "area": "SAN JUAN"
    },
    {
      "zone": "Urb. Gonzalez Seijo",
      "area": "SAN JUAN"
    },
    {
      "zone": "Urb. La Riviera",
      "area": "SAN JUAN"
    },
    {
      "zone": "Urb. Las Virtudes",
      "area": "SAN JUAN"
    },
    {
      "zone": "Urb. Puerto Nuevo Calles NO",
      "area": "SAN JUAN"
    },
    {
      "zone": "Urb. Roosevelt",
      "area": "SAN JUAN"
    },
    {
      "zone": "Urb. San Gerardo",
      "area": "SAN JUAN"
    },
    {
      "zone": "Urb. Santiago Iglesias",
      "area": "SAN JUAN"
    },
    {
      "zone": "Urb. Venus Gard. Oeste",
      "area": "SAN JUAN"
    },
    {
      "zone": "Urb. Villa Navarra",
      "area": "SAN JUAN"
    },
    {
      "zone": "Urb. Villa Nevares",
      "area": "SAN JUAN"
    },
    {
      "zone": "Viejo San Juan",
      "area": "SAN JUAN"
    },
    {
      "zone": "Zona Portuaria",
      "area": "SAN JUAN"
    }
  ],
  "BAYAMON": [
    {
      "zone": "BO SANTA OLAYA/SEC EL PUNTO",
      "area": "BAYAMON"
    },
    {
      "zone": "Bo. Dajaos",
      "area": "BAYAMON"
    },
    {
      "zone": "Bo. Juan Sanchez",
      "area": "BAYAMON"
    },
    {
      "zone": "MINILLAS",
      "area": "BAYAMON"
    },
    {
      "zone": "RIO PLANTATIONHATO TEJAS",
      "area": "BAYAMON"
    },
    {
      "zone": "SANTA OLAYA",
      "area": "BAYAMON"
    },
    {
      "zone": "URB PUB BRISAS DE BAYAMON",
      "area": "BAYAMON"
    },
    {
      "zone": "Urb. Alhambra",
      "area": "BAYAMON"
    },
    {
      "zone": "Urb. Jardines de Caparra",
      "area": "BAYAMON"
    }
  ]
}
