{
  "CATANO": [],
  "CAROLINA": [],
  "TRUJILLO ALTO": [],
  "GUAYNABO": [
    {
      "zone": "Ave. Martinez Nadal",
      "area": "GUAYNABO"
    }
  ],
  "SAN JUAN": [
    {
      "zone": "MONACILLO URBANO",
      "area": "SAN JUAN"
    },
    {
      "zone": "RIO PIEDRAS HEIGHTS",
      "area": "SAN JUAN"
    },
    {
      "zone": "URB BALDRICH",
      "area": "SAN JUAN"
    },
    {
      "zone": "URB LAS AMERICAS",
      "area": "SAN JUAN"
    },
    {
      "zone": "URB SANTA MARIA",
      "area": "SAN JUAN"
    }
  ],
  "BAYAMON": [
    {
      "zone": "Bo. Buena Vista",
      "area": "BAYAMON"
    },
    {
      "zone": "URB RESIDENCIAL CANA",
      "area": "BAYAMON"
    }
  ]
}
