{
  "regions": [
    {
      "name": "Arecibo",
      "totalClients": 177369,
      "totalClientsWithoutService": 673,
      "totalClientsWithService": 176696,
      "percentageClientsWithoutService": 0.38,
      "percentageClientsWithService": 99.62
    },
    {
      "name": "Bayamon",
      "totalClients": 216496,
      "totalClientsWithoutService": 867,
      "totalClientsWithService": 215629,
      "percentageClientsWithoutService": 0.4,
      "percentageClientsWithService": 99.6
    },
    {
      "name": "Carolina",
      "totalClients": 141663,
      "totalClientsWithoutService": 10,
      "totalClientsWithService": 141653,
      "percentageClientsWithoutService": 0.01,
      "percentageClientsWithService": 99.99
    },
    {
      "name": "Caguas",
      "totalClients": 250514,
      "totalClientsWithoutService": 1038,
      "totalClientsWithService": 249476,
      "percentageClientsWithoutService": 0.41,
      "percentageClientsWithService": 99.59
    },
    {
      "name": "Mayaguez",
      "totalClients": 216605,
      "totalClientsWithoutService": 96,
      "totalClientsWithService": 216509,
      "percentageClientsWithoutService": 0.04,
      "percentageClientsWithService": 99.96
    },
    {
      "name": "Ponce",
      "totalClients": 212508,
      "totalClientsWithoutService": 2114,
      "totalClientsWithService": 210394,
      "percentageClientsWithoutService": 0.99,
      "percentageClientsWithService": 99.01
    },
    {
      "name": "San Juan",
      "totalClients": 253068,
      "totalClientsWithoutService": 7673,
      "totalClientsWithService": 245395,
      "percentageClientsWithoutService": 3.03,
      "percentageClientsWithService": 96.97
    }
  ],
  "totals": {
    "totalClientsWithoutService": 12471,
    "totalClients": 1468223,
    "totalClientsWithService": 1455752,
    "totalPercentageWithoutService": 0.85,
    "totalPercentageWithService": 99.15
  },
  "timestamp": "10/20/2023 11:45 AM"
}
