{
  "regions": [
    {
      "name": "Arecibo",
      "totalClients": 177369,
      "totalClientsWithoutService": 682,
      "totalClientsWithService": 176687,
      "totalClientsAffectedByPlannedOutage": 0,
      "percentageClientsWithoutService": 0.38,
      "percentageClientsWithService": 99.62
    },
    {
      "name": "Mayaguez",
      "totalClients": 216605,
      "totalClientsWithoutService": 190,
      "totalClientsWithService": 216415,
      "totalClientsAffectedByPlannedOutage": 0,
      "percentageClientsWithoutService": 0.09,
      "percentageClientsWithService": 99.91
    },
    {
      "name": "Bayamon",
      "totalClients": 216496,
      "totalClientsWithoutService": 132,
      "totalClientsWithService": 216364,
      "totalClientsAffectedByPlannedOutage": 0,
      "percentageClientsWithoutService": 0.06,
      "percentageClientsWithService": 99.94
    },
    {
      "name": "San Juan",
      "totalClients": 253068,
      "totalClientsWithoutService": 87,
      "totalClientsWithService": 252981,
      "totalClientsAffectedByPlannedOutage": 64,
      "percentageClientsWithoutService": 0.03,
      "percentageClientsWithService": 99.97
    },
    {
      "name": "Carolina",
      "totalClients": 141663,
      "totalClientsWithoutService": 11,
      "totalClientsWithService": 141652,
      "totalClientsAffectedByPlannedOutage": 10,
      "percentageClientsWithoutService": 0.01,
      "percentageClientsWithService": 99.99
    },
    {
      "name": "Ponce",
      "totalClients": 212508,
      "totalClientsWithoutService": 111,
      "totalClientsWithService": 212397,
      "totalClientsAffectedByPlannedOutage": 0,
      "percentageClientsWithoutService": 0.05,
      "percentageClientsWithService": 99.95
    },
    {
      "name": "Caguas",
      "totalClients": 250514,
      "totalClientsWithoutService": 1676,
      "totalClientsWithService": 248838,
      "totalClientsAffectedByPlannedOutage": 76,
      "percentageClientsWithoutService": 0.67,
      "percentageClientsWithService": 99.33
    }
  ],
  "totals": {
    "totalClientsWithoutService": 2889,
    "totalClients": 1468223,
    "totalClientsWithService": 1465334,
    "totalPercentageWithoutService": 0.2,
    "totalClientsAffectedByPlannedOutage": 150,
    "totalPercentageWithService": 99.8
  },
  "timestamp": "04/20/2024 09:10 AM"
}
