{
  "regions": [
    {
      "name": "Arecibo",
      "totalClients": 177369,
      "totalClientsWithoutService": 85,
      "totalClientsWithService": 177284,
      "totalClientsAffectedByPlannedOutage": 0,
      "percentageClientsWithoutService": 0.05,
      "percentageClientsWithService": 99.95
    },
    {
      "name": "Bayamon",
      "totalClients": 216496,
      "totalClientsWithoutService": 872,
      "totalClientsWithService": 215624,
      "totalClientsAffectedByPlannedOutage": 484,
      "percentageClientsWithoutService": 0.4,
      "percentageClientsWithService": 99.6
    },
    {
      "name": "Mayaguez",
      "totalClients": 216605,
      "totalClientsWithoutService": 1475,
      "totalClientsWithService": 215130,
      "totalClientsAffectedByPlannedOutage": 345,
      "percentageClientsWithoutService": 0.68,
      "percentageClientsWithService": 99.32
    },
    {
      "name": "San Juan",
      "totalClients": 253068,
      "totalClientsWithoutService": 1813,
      "totalClientsWithService": 251255,
      "totalClientsAffectedByPlannedOutage": 1423,
      "percentageClientsWithoutService": 0.72,
      "percentageClientsWithService": 99.28
    },
    {
      "name": "Carolina",
      "totalClients": 141663,
      "totalClientsWithoutService": 180,
      "totalClientsWithService": 141483,
      "totalClientsAffectedByPlannedOutage": 4,
      "percentageClientsWithoutService": 0.13,
      "percentageClientsWithService": 99.87
    },
    {
      "name": "Ponce",
      "totalClients": 212508,
      "totalClientsWithoutService": 959,
      "totalClientsWithService": 211549,
      "totalClientsAffectedByPlannedOutage": 565,
      "percentageClientsWithoutService": 0.45,
      "percentageClientsWithService": 99.55
    },
    {
      "name": "Caguas",
      "totalClients": 250514,
      "totalClientsWithoutService": 706,
      "totalClientsWithService": 249808,
      "totalClientsAffectedByPlannedOutage": 115,
      "percentageClientsWithoutService": 0.28,
      "percentageClientsWithService": 99.72
    }
  ],
  "totals": {
    "totalClientsWithoutService": 6090,
    "totalClients": 1468223,
    "totalClientsWithService": 1462133,
    "totalPercentageWithoutService": 0.41,
    "totalClientsAffectedByPlannedOutage": 2936,
    "totalPercentageWithService": 99.59
  },
  "timestamp": "05/01/2024 11:40 AM"
}
