{
  "regions": [
    {
      "name": "Arecibo",
      "totalClients": 177369,
      "totalClientsWithoutService": 76,
      "totalClientsWithService": 177293,
      "percentageClientsWithoutService": 0.04,
      "percentageClientsWithService": 99.96
    },
    {
      "name": "Bayamon",
      "totalClients": 216496,
      "totalClientsWithoutService": 197,
      "totalClientsWithService": 216299,
      "percentageClientsWithoutService": 0.09,
      "percentageClientsWithService": 99.91
    },
    {
      "name": "Carolina",
      "totalClients": 141663,
      "totalClientsWithoutService": 103,
      "totalClientsWithService": 141560,
      "percentageClientsWithoutService": 0.07,
      "percentageClientsWithService": 99.93
    },
    {
      "name": "Caguas",
      "totalClients": 250514,
      "totalClientsWithoutService": 877,
      "totalClientsWithService": 249637,
      "percentageClientsWithoutService": 0.35,
      "percentageClientsWithService": 99.65
    },
    {
      "name": "Mayaguez",
      "totalClients": 216605,
      "totalClientsWithoutService": 433,
      "totalClientsWithService": 216172,
      "percentageClientsWithoutService": 0.2,
      "percentageClientsWithService": 99.8
    },
    {
      "name": "Ponce",
      "totalClients": 212508,
      "totalClientsWithoutService": 13,
      "totalClientsWithService": 212495,
      "percentageClientsWithoutService": 0.01,
      "percentageClientsWithService": 99.99
    },
    {
      "name": "San Juan",
      "totalClients": 253068,
      "totalClientsWithoutService": 29,
      "totalClientsWithService": 253039,
      "percentageClientsWithoutService": 0.01,
      "percentageClientsWithService": 99.99
    }
  ],
  "totals": {
    "totalClientsWithoutService": 1728,
    "totalClients": 1468223,
    "totalClientsWithService": 1466495,
    "totalPercentageWithoutService": 0.12,
    "totalPercentageWithService": 99.88
  },
  "timestamp": "10/23/2023 07:25 AM"
}
