{
  "regions": [
    {
      "name": "Arecibo",
      "totalClients": 177369,
      "totalClientsWithoutService": 52,
      "totalClientsWithService": 177317,
      "totalClientsAffectedByPlannedOutage": 24,
      "percentageClientsWithoutService": 0.03,
      "percentageClientsWithService": 99.97
    },
    {
      "name": "Mayaguez",
      "totalClients": 216605,
      "totalClientsWithoutService": 241,
      "totalClientsWithService": 216364,
      "totalClientsAffectedByPlannedOutage": 0,
      "percentageClientsWithoutService": 0.11,
      "percentageClientsWithService": 99.89
    },
    {
      "name": "Bayamon",
      "totalClients": 216496,
      "totalClientsWithoutService": 1374,
      "totalClientsWithService": 215122,
      "totalClientsAffectedByPlannedOutage": 1348,
      "percentageClientsWithoutService": 0.63,
      "percentageClientsWithService": 99.37
    },
    {
      "name": "San Juan",
      "totalClients": 253068,
      "totalClientsWithoutService": 586,
      "totalClientsWithService": 252482,
      "totalClientsAffectedByPlannedOutage": 0,
      "percentageClientsWithoutService": 0.23,
      "percentageClientsWithService": 99.77
    },
    {
      "name": "Carolina",
      "totalClients": 141663,
      "totalClientsWithoutService": 78,
      "totalClientsWithService": 141585,
      "totalClientsAffectedByPlannedOutage": 14,
      "percentageClientsWithoutService": 0.06,
      "percentageClientsWithService": 99.94
    },
    {
      "name": "Caguas",
      "totalClients": 250514,
      "totalClientsWithoutService": 4170,
      "totalClientsWithService": 246344,
      "totalClientsAffectedByPlannedOutage": 773,
      "percentageClientsWithoutService": 1.66,
      "percentageClientsWithService": 98.34
    },
    {
      "name": "Ponce",
      "totalClients": 212508,
      "totalClientsWithoutService": 203,
      "totalClientsWithService": 212305,
      "totalClientsAffectedByPlannedOutage": 183,
      "percentageClientsWithoutService": 0.1,
      "percentageClientsWithService": 99.9
    }
  ],
  "totals": {
    "totalClientsWithoutService": 6704,
    "totalClients": 1468223,
    "totalClientsWithService": 1461519,
    "totalPercentageWithoutService": 0.46,
    "totalClientsAffectedByPlannedOutage": 2342,
    "totalPercentageWithService": 99.54
  },
  "timestamp": "03/01/2024 03:15 PM"
}
