{
  "regions": [
    {
      "name": "Arecibo",
      "totalClients": 177369,
      "totalClientsWithoutService": 500,
      "totalClientsWithService": 176869,
      "percentageClientsWithoutService": 0.28,
      "percentageClientsWithService": 99.72
    },
    {
      "name": "Bayamon",
      "totalClients": 216496,
      "totalClientsWithoutService": 301,
      "totalClientsWithService": 216195,
      "percentageClientsWithoutService": 0.14,
      "percentageClientsWithService": 99.86
    },
    {
      "name": "Carolina",
      "totalClients": 141663,
      "totalClientsWithoutService": 1306,
      "totalClientsWithService": 140357,
      "percentageClientsWithoutService": 0.92,
      "percentageClientsWithService": 99.08
    },
    {
      "name": "Caguas",
      "totalClients": 250514,
      "totalClientsWithoutService": 226,
      "totalClientsWithService": 250288,
      "percentageClientsWithoutService": 0.09,
      "percentageClientsWithService": 99.91
    },
    {
      "name": "Mayaguez",
      "totalClients": 216605,
      "totalClientsWithoutService": 1066,
      "totalClientsWithService": 215539,
      "percentageClientsWithoutService": 0.49,
      "percentageClientsWithService": 99.51
    },
    {
      "name": "Ponce",
      "totalClients": 212508,
      "totalClientsWithoutService": 1893,
      "totalClientsWithService": 210615,
      "percentageClientsWithoutService": 0.89,
      "percentageClientsWithService": 99.11
    },
    {
      "name": "San Juan",
      "totalClients": 253068,
      "totalClientsWithoutService": 453,
      "totalClientsWithService": 252615,
      "percentageClientsWithoutService": 0.18,
      "percentageClientsWithService": 99.82
    }
  ],
  "totals": {
    "totalClientsWithoutService": 5745,
    "totalClients": 1468223,
    "totalClientsWithService": 1462478,
    "totalPercentageWithoutService": 0.39,
    "totalPercentageWithService": 99.61
  },
  "timestamp": "11/28/2023 01:35 PM"
}
