{
  "regions": [
    {
      "name": "Arecibo",
      "totalClients": 177369,
      "totalClientsWithoutService": 1303,
      "totalClientsWithService": 176066,
      "totalClientsAffectedByPlannedOutage": 0,
      "percentageClientsWithoutService": 0.73,
      "percentageClientsWithService": 99.27
    },
    {
      "name": "Bayamon",
      "totalClients": 216496,
      "totalClientsWithoutService": 193,
      "totalClientsWithService": 216303,
      "totalClientsAffectedByPlannedOutage": 0,
      "percentageClientsWithoutService": 0.09,
      "percentageClientsWithService": 99.91
    },
    {
      "name": "Mayaguez",
      "totalClients": 216605,
      "totalClientsWithoutService": 60,
      "totalClientsWithService": 216545,
      "totalClientsAffectedByPlannedOutage": 0,
      "percentageClientsWithoutService": 0.03,
      "percentageClientsWithService": 99.97
    },
    {
      "name": "San Juan",
      "totalClients": 253068,
      "totalClientsWithoutService": 179,
      "totalClientsWithService": 252889,
      "totalClientsAffectedByPlannedOutage": 0,
      "percentageClientsWithoutService": 0.07,
      "percentageClientsWithService": 99.93
    },
    {
      "name": "Carolina",
      "totalClients": 141663,
      "totalClientsWithoutService": 73,
      "totalClientsWithService": 141590,
      "totalClientsAffectedByPlannedOutage": 0,
      "percentageClientsWithoutService": 0.05,
      "percentageClientsWithService": 99.95
    },
    {
      "name": "Ponce",
      "totalClients": 212508,
      "totalClientsWithoutService": 276,
      "totalClientsWithService": 212232,
      "totalClientsAffectedByPlannedOutage": 0,
      "percentageClientsWithoutService": 0.13,
      "percentageClientsWithService": 99.87
    },
    {
      "name": "Caguas",
      "totalClients": 250514,
      "totalClientsWithoutService": 419,
      "totalClientsWithService": 250095,
      "totalClientsAffectedByPlannedOutage": 0,
      "percentageClientsWithoutService": 0.17,
      "percentageClientsWithService": 99.83
    }
  ],
  "totals": {
    "totalClientsWithoutService": 2503,
    "totalClients": 1468223,
    "totalClientsWithService": 1465720,
    "totalPercentageWithoutService": 0.17,
    "totalClientsAffectedByPlannedOutage": 0,
    "totalPercentageWithService": 99.83
  },
  "timestamp": "06/06/2024 02:35 PM"
}
