{
  "regions": [
    {
      "name": "Arecibo",
      "totalClients": 177369,
      "totalClientsWithoutService": 50,
      "totalClientsWithService": 177319,
      "percentageClientsWithoutService": 0.03,
      "percentageClientsWithService": 99.97
    },
    {
      "name": "Bayamon",
      "totalClients": 216496,
      "totalClientsWithoutService": 4661,
      "totalClientsWithService": 211835,
      "percentageClientsWithoutService": 2.15,
      "percentageClientsWithService": 97.85
    },
    {
      "name": "Carolina",
      "totalClients": 141663,
      "totalClientsWithoutService": 159,
      "totalClientsWithService": 141504,
      "percentageClientsWithoutService": 0.11,
      "percentageClientsWithService": 99.89
    },
    {
      "name": "Caguas",
      "totalClients": 250514,
      "totalClientsWithoutService": 799,
      "totalClientsWithService": 249715,
      "percentageClientsWithoutService": 0.32,
      "percentageClientsWithService": 99.68
    },
    {
      "name": "Mayaguez",
      "totalClients": 216605,
      "totalClientsWithoutService": 22,
      "totalClientsWithService": 216583,
      "percentageClientsWithoutService": 0.01,
      "percentageClientsWithService": 99.99
    },
    {
      "name": "Ponce",
      "totalClients": 212508,
      "totalClientsWithoutService": 192,
      "totalClientsWithService": 212316,
      "percentageClientsWithoutService": 0.09,
      "percentageClientsWithService": 99.91
    },
    {
      "name": "San Juan",
      "totalClients": 253068,
      "totalClientsWithoutService": 34,
      "totalClientsWithService": 253034,
      "percentageClientsWithoutService": 0.01,
      "percentageClientsWithService": 99.99
    }
  ],
  "totals": {
    "totalClientsWithoutService": 5917,
    "totalClients": 1468223,
    "totalClientsWithService": 1462306,
    "totalPercentageWithoutService": 0.4,
    "totalPercentageWithService": 99.6
  },
  "timestamp": "10/10/2023 07:55 AM"
}
