{
  "regions": [
    {
      "name": "Arecibo",
      "totalClients": 177369,
      "totalClientsWithoutService": 29,
      "totalClientsWithService": 177340,
      "percentageClientsWithoutService": 0.02,
      "percentageClientsWithService": 99.98
    },
    {
      "name": "Bayamon",
      "totalClients": 216496,
      "totalClientsWithoutService": 96,
      "totalClientsWithService": 216400,
      "percentageClientsWithoutService": 0.04,
      "percentageClientsWithService": 99.96
    },
    {
      "name": "Carolina",
      "totalClients": 141663,
      "totalClientsWithoutService": 5,
      "totalClientsWithService": 141658,
      "percentageClientsWithoutService": 0,
      "percentageClientsWithService": 100
    },
    {
      "name": "Caguas",
      "totalClients": 250514,
      "totalClientsWithoutService": 548,
      "totalClientsWithService": 249966,
      "percentageClientsWithoutService": 0.22,
      "percentageClientsWithService": 99.78
    },
    {
      "name": "Mayaguez",
      "totalClients": 216605,
      "totalClientsWithoutService": 118,
      "totalClientsWithService": 216487,
      "percentageClientsWithoutService": 0.05,
      "percentageClientsWithService": 99.95
    },
    {
      "name": "Ponce",
      "totalClients": 212508,
      "totalClientsWithoutService": 28,
      "totalClientsWithService": 212480,
      "percentageClientsWithoutService": 0.01,
      "percentageClientsWithService": 99.99
    },
    {
      "name": "San Juan",
      "totalClients": 253068,
      "totalClientsWithoutService": 873,
      "totalClientsWithService": 252195,
      "percentageClientsWithoutService": 0.34,
      "percentageClientsWithService": 99.66
    }
  ],
  "totals": {
    "totalClientsWithoutService": 1697,
    "totalClients": 1468223,
    "totalClientsWithService": 1466526,
    "totalPercentageWithoutService": 0.12,
    "totalPercentageWithService": 99.88
  },
  "timestamp": "10/30/2023 06:05 PM"
}
