{
  "regions": [
    {
      "name": "Arecibo",
      "totalClients": 177369,
      "totalClientsWithoutService": 452,
      "totalClientsWithService": 176917,
      "percentageClientsWithoutService": 0.25,
      "percentageClientsWithService": 99.75
    },
    {
      "name": "Bayamon",
      "totalClients": 216496,
      "totalClientsWithoutService": 1552,
      "totalClientsWithService": 214944,
      "percentageClientsWithoutService": 0.72,
      "percentageClientsWithService": 99.28
    },
    {
      "name": "Carolina",
      "totalClients": 141663,
      "totalClientsWithoutService": 4,
      "totalClientsWithService": 141659,
      "percentageClientsWithoutService": 0,
      "percentageClientsWithService": 100
    },
    {
      "name": "Caguas",
      "totalClients": 250514,
      "totalClientsWithoutService": 303,
      "totalClientsWithService": 250211,
      "percentageClientsWithoutService": 0.12,
      "percentageClientsWithService": 99.88
    },
    {
      "name": "Mayaguez",
      "totalClients": 216605,
      "totalClientsWithoutService": 281,
      "totalClientsWithService": 216324,
      "percentageClientsWithoutService": 0.13,
      "percentageClientsWithService": 99.87
    },
    {
      "name": "Ponce",
      "totalClients": 212508,
      "totalClientsWithoutService": 32,
      "totalClientsWithService": 212476,
      "percentageClientsWithoutService": 0.02,
      "percentageClientsWithService": 99.98
    },
    {
      "name": "San Juan",
      "totalClients": 253068,
      "totalClientsWithoutService": 497,
      "totalClientsWithService": 252571,
      "percentageClientsWithoutService": 0.2,
      "percentageClientsWithService": 99.8
    }
  ],
  "totals": {
    "totalClientsWithoutService": 3121,
    "totalClients": 1468223,
    "totalClientsWithService": 1465102,
    "totalPercentageWithoutService": 0.21,
    "totalPercentageWithService": 99.79
  },
  "timestamp": "09/26/2023 09:25 AM"
}
