{
  "regions": [
    {
      "name": "Arecibo",
      "totalClients": 177369,
      "totalClientsWithoutService": 939,
      "totalClientsWithService": 176430,
      "totalClientsAffectedByPlannedOutage": 0,
      "percentageClientsWithoutService": 0.53,
      "percentageClientsWithService": 99.47
    },
    {
      "name": "Bayamon",
      "totalClients": 216496,
      "totalClientsWithoutService": 342,
      "totalClientsWithService": 216154,
      "totalClientsAffectedByPlannedOutage": 0,
      "percentageClientsWithoutService": 0.16,
      "percentageClientsWithService": 99.84
    },
    {
      "name": "Mayaguez",
      "totalClients": 216605,
      "totalClientsWithoutService": 984,
      "totalClientsWithService": 215621,
      "totalClientsAffectedByPlannedOutage": 0,
      "percentageClientsWithoutService": 0.45,
      "percentageClientsWithService": 99.55
    },
    {
      "name": "San Juan",
      "totalClients": 253068,
      "totalClientsWithoutService": 1916,
      "totalClientsWithService": 251152,
      "totalClientsAffectedByPlannedOutage": 19,
      "percentageClientsWithoutService": 0.76,
      "percentageClientsWithService": 99.24
    },
    {
      "name": "Carolina",
      "totalClients": 141663,
      "totalClientsWithoutService": 198,
      "totalClientsWithService": 141465,
      "totalClientsAffectedByPlannedOutage": 35,
      "percentageClientsWithoutService": 0.14,
      "percentageClientsWithService": 99.86
    },
    {
      "name": "Caguas",
      "totalClients": 250514,
      "totalClientsWithoutService": 1155,
      "totalClientsWithService": 249359,
      "totalClientsAffectedByPlannedOutage": 161,
      "percentageClientsWithoutService": 0.46,
      "percentageClientsWithService": 99.54
    },
    {
      "name": "Ponce",
      "totalClients": 212508,
      "totalClientsWithoutService": 360,
      "totalClientsWithService": 212148,
      "totalClientsAffectedByPlannedOutage": 0,
      "percentageClientsWithoutService": 0.17,
      "percentageClientsWithService": 99.83
    }
  ],
  "totals": {
    "totalClientsWithoutService": 5894,
    "totalClients": 1468223,
    "totalClientsWithService": 1462329,
    "totalPercentageWithoutService": 0.4,
    "totalClientsAffectedByPlannedOutage": 215,
    "totalPercentageWithService": 99.6
  },
  "timestamp": "05/29/2024 08:45 AM"
}
