{
  "regions": [
    {
      "name": "Arecibo",
      "totalClients": 177369,
      "totalClientsWithoutService": 4166,
      "totalClientsWithService": 173203,
      "totalClientsAffectedByPlannedOutage": 0,
      "percentageClientsWithoutService": 2.35,
      "percentageClientsWithService": 97.65
    },
    {
      "name": "Bayamon",
      "totalClients": 216496,
      "totalClientsWithoutService": 816,
      "totalClientsWithService": 215680,
      "totalClientsAffectedByPlannedOutage": 493,
      "percentageClientsWithoutService": 0.38,
      "percentageClientsWithService": 99.62
    },
    {
      "name": "Mayaguez",
      "totalClients": 216605,
      "totalClientsWithoutService": 178,
      "totalClientsWithService": 216427,
      "totalClientsAffectedByPlannedOutage": 65,
      "percentageClientsWithoutService": 0.08,
      "percentageClientsWithService": 99.92
    },
    {
      "name": "San Juan",
      "totalClients": 253068,
      "totalClientsWithoutService": 217,
      "totalClientsWithService": 252851,
      "totalClientsAffectedByPlannedOutage": 0,
      "percentageClientsWithoutService": 0.09,
      "percentageClientsWithService": 99.91
    },
    {
      "name": "Carolina",
      "totalClients": 141663,
      "totalClientsWithoutService": 304,
      "totalClientsWithService": 141359,
      "totalClientsAffectedByPlannedOutage": 251,
      "percentageClientsWithoutService": 0.21,
      "percentageClientsWithService": 99.79
    },
    {
      "name": "Caguas",
      "totalClients": 250514,
      "totalClientsWithoutService": 453,
      "totalClientsWithService": 250061,
      "totalClientsAffectedByPlannedOutage": 265,
      "percentageClientsWithoutService": 0.18,
      "percentageClientsWithService": 99.82
    },
    {
      "name": "Ponce",
      "totalClients": 212508,
      "totalClientsWithoutService": 7567,
      "totalClientsWithService": 204941,
      "totalClientsAffectedByPlannedOutage": 0,
      "percentageClientsWithoutService": 3.56,
      "percentageClientsWithService": 96.44
    }
  ],
  "totals": {
    "totalClientsWithoutService": 13701,
    "totalClients": 1468223,
    "totalClientsWithService": 1454522,
    "totalPercentageWithoutService": 0.93,
    "totalClientsAffectedByPlannedOutage": 1074,
    "totalPercentageWithService": 99.07
  },
  "timestamp": "04/24/2024 01:45 PM"
}
