{
  "regions": [
    {
      "name": "Arecibo",
      "totalClients": 177369,
      "totalClientsWithoutService": 168,
      "totalClientsWithService": 177201,
      "percentageClientsWithoutService": 0.09,
      "percentageClientsWithService": 99.91
    },
    {
      "name": "Bayamon",
      "totalClients": 216496,
      "totalClientsWithoutService": 5,
      "totalClientsWithService": 216491,
      "percentageClientsWithoutService": 0,
      "percentageClientsWithService": 100
    },
    {
      "name": "Carolina",
      "totalClients": 141663,
      "totalClientsWithoutService": 35,
      "totalClientsWithService": 141628,
      "percentageClientsWithoutService": 0.02,
      "percentageClientsWithService": 99.98
    },
    {
      "name": "Caguas",
      "totalClients": 250514,
      "totalClientsWithoutService": 40,
      "totalClientsWithService": 250474,
      "percentageClientsWithoutService": 0.02,
      "percentageClientsWithService": 99.98
    },
    {
      "name": "Mayaguez",
      "totalClients": 216605,
      "totalClientsWithoutService": 2193,
      "totalClientsWithService": 214412,
      "percentageClientsWithoutService": 1.01,
      "percentageClientsWithService": 98.99
    },
    {
      "name": "Ponce",
      "totalClients": 212508,
      "totalClientsWithoutService": 116,
      "totalClientsWithService": 212392,
      "percentageClientsWithoutService": 0.05,
      "percentageClientsWithService": 99.95
    },
    {
      "name": "San Juan",
      "totalClients": 253068,
      "totalClientsWithoutService": 963,
      "totalClientsWithService": 252105,
      "percentageClientsWithoutService": 0.38,
      "percentageClientsWithService": 99.62
    }
  ],
  "totals": {
    "totalClientsWithoutService": 3520,
    "totalClients": 1468223,
    "totalClientsWithService": 1464703,
    "totalPercentageWithoutService": 0.24,
    "totalPercentageWithService": 99.76
  },
  "timestamp": "01/29/2024 04:10 PM"
}
