{
  "regions": [
    {
      "name": "Arecibo",
      "totalClients": 177369,
      "totalClientsWithoutService": 195,
      "totalClientsWithService": 177174,
      "percentageClientsWithoutService": 0.11,
      "percentageClientsWithService": 99.89
    },
    {
      "name": "Bayamon",
      "totalClients": 216496,
      "totalClientsWithoutService": 2304,
      "totalClientsWithService": 214192,
      "percentageClientsWithoutService": 1.06,
      "percentageClientsWithService": 98.94
    },
    {
      "name": "Carolina",
      "totalClients": 141663,
      "totalClientsWithoutService": 1014,
      "totalClientsWithService": 140649,
      "percentageClientsWithoutService": 0.72,
      "percentageClientsWithService": 99.28
    },
    {
      "name": "Caguas",
      "totalClients": 250514,
      "totalClientsWithoutService": 2393,
      "totalClientsWithService": 248121,
      "percentageClientsWithoutService": 0.96,
      "percentageClientsWithService": 99.04
    },
    {
      "name": "Mayaguez",
      "totalClients": 216605,
      "totalClientsWithoutService": 3217,
      "totalClientsWithService": 213388,
      "percentageClientsWithoutService": 1.49,
      "percentageClientsWithService": 98.51
    },
    {
      "name": "Ponce",
      "totalClients": 212508,
      "totalClientsWithoutService": 1,
      "totalClientsWithService": 212507,
      "percentageClientsWithoutService": 0,
      "percentageClientsWithService": 100
    },
    {
      "name": "San Juan",
      "totalClients": 253068,
      "totalClientsWithoutService": 940,
      "totalClientsWithService": 252128,
      "percentageClientsWithoutService": 0.37,
      "percentageClientsWithService": 99.63
    }
  ],
  "totals": {
    "totalClientsWithoutService": 10064,
    "totalClients": 1468223,
    "totalClientsWithService": 1458159,
    "totalPercentageWithoutService": 0.69,
    "totalPercentageWithService": 99.31
  },
  "timestamp": "09/20/2023 10:05 PM"
}
