{
  "regions": [
    {
      "name": "Arecibo",
      "totalClients": 177369,
      "totalClientsWithoutService": 379,
      "totalClientsWithService": 176990,
      "totalClientsAffectedByPlannedOutage": 9,
      "percentageClientsWithoutService": 0.21,
      "percentageClientsWithService": 99.79
    },
    {
      "name": "Bayamon",
      "totalClients": 216496,
      "totalClientsWithoutService": 730,
      "totalClientsWithService": 215766,
      "totalClientsAffectedByPlannedOutage": 0,
      "percentageClientsWithoutService": 0.34,
      "percentageClientsWithService": 99.66
    },
    {
      "name": "Mayaguez",
      "totalClients": 216605,
      "totalClientsWithoutService": 2206,
      "totalClientsWithService": 214399,
      "totalClientsAffectedByPlannedOutage": 0,
      "percentageClientsWithoutService": 1.02,
      "percentageClientsWithService": 98.98
    },
    {
      "name": "San Juan",
      "totalClients": 253068,
      "totalClientsWithoutService": 654,
      "totalClientsWithService": 252414,
      "totalClientsAffectedByPlannedOutage": 0,
      "percentageClientsWithoutService": 0.26,
      "percentageClientsWithService": 99.74
    },
    {
      "name": "Carolina",
      "totalClients": 141663,
      "totalClientsWithoutService": 1991,
      "totalClientsWithService": 139672,
      "totalClientsAffectedByPlannedOutage": 0,
      "percentageClientsWithoutService": 1.41,
      "percentageClientsWithService": 98.59
    },
    {
      "name": "Ponce",
      "totalClients": 212508,
      "totalClientsWithoutService": 6073,
      "totalClientsWithService": 206435,
      "totalClientsAffectedByPlannedOutage": 0,
      "percentageClientsWithoutService": 2.86,
      "percentageClientsWithService": 97.14
    },
    {
      "name": "Caguas",
      "totalClients": 250514,
      "totalClientsWithoutService": 863,
      "totalClientsWithService": 249651,
      "totalClientsAffectedByPlannedOutage": 432,
      "percentageClientsWithoutService": 0.34,
      "percentageClientsWithService": 99.66
    }
  ],
  "totals": {
    "totalClientsWithoutService": 12896,
    "totalClients": 1468223,
    "totalClientsWithService": 1455327,
    "totalPercentageWithoutService": 0.88,
    "totalClientsAffectedByPlannedOutage": 441,
    "totalPercentageWithService": 99.12
  },
  "timestamp": "06/10/2024 04:55 PM"
}
