{
  "regions": [
    {
      "name": "Arecibo",
      "totalClients": 177369,
      "totalClientsWithoutService": 406,
      "totalClientsWithService": 176963,
      "totalClientsAffectedByPlannedOutage": 5,
      "percentageClientsWithoutService": 0.23,
      "percentageClientsWithService": 99.77
    },
    {
      "name": "Bayamon",
      "totalClients": 216496,
      "totalClientsWithoutService": 568,
      "totalClientsWithService": 215928,
      "totalClientsAffectedByPlannedOutage": 238,
      "percentageClientsWithoutService": 0.26,
      "percentageClientsWithService": 99.74
    },
    {
      "name": "Mayaguez",
      "totalClients": 216605,
      "totalClientsWithoutService": 398,
      "totalClientsWithService": 216207,
      "totalClientsAffectedByPlannedOutage": 47,
      "percentageClientsWithoutService": 0.18,
      "percentageClientsWithService": 99.82
    },
    {
      "name": "San Juan",
      "totalClients": 253068,
      "totalClientsWithoutService": 890,
      "totalClientsWithService": 252178,
      "totalClientsAffectedByPlannedOutage": 523,
      "percentageClientsWithoutService": 0.35,
      "percentageClientsWithService": 99.65
    },
    {
      "name": "Carolina",
      "totalClients": 141663,
      "totalClientsWithoutService": 1347,
      "totalClientsWithService": 140316,
      "totalClientsAffectedByPlannedOutage": 1334,
      "percentageClientsWithoutService": 0.95,
      "percentageClientsWithService": 99.05
    },
    {
      "name": "Caguas",
      "totalClients": 250514,
      "totalClientsWithoutService": 1163,
      "totalClientsWithService": 249351,
      "totalClientsAffectedByPlannedOutage": 862,
      "percentageClientsWithoutService": 0.46,
      "percentageClientsWithService": 99.54
    },
    {
      "name": "Ponce",
      "totalClients": 212508,
      "totalClientsWithoutService": 3821,
      "totalClientsWithService": 208687,
      "totalClientsAffectedByPlannedOutage": 3817,
      "percentageClientsWithoutService": 1.8,
      "percentageClientsWithService": 98.2
    }
  ],
  "totals": {
    "totalClientsWithoutService": 8593,
    "totalClients": 1468223,
    "totalClientsWithService": 1459630,
    "totalPercentageWithoutService": 0.59,
    "totalClientsAffectedByPlannedOutage": 6826,
    "totalPercentageWithService": 99.41
  },
  "timestamp": "05/16/2024 11:15 AM"
}
