{
  "regions": [
    {
      "name": "Arecibo",
      "totalClients": 177369,
      "totalClientsWithoutService": 6892,
      "totalClientsWithService": 170477,
      "totalClientsAffectedByPlannedOutage": 6805,
      "percentageClientsWithoutService": 3.89,
      "percentageClientsWithService": 96.11
    },
    {
      "name": "Mayaguez",
      "totalClients": 216605,
      "totalClientsWithoutService": 8319,
      "totalClientsWithService": 208286,
      "totalClientsAffectedByPlannedOutage": 6886,
      "percentageClientsWithoutService": 3.84,
      "percentageClientsWithService": 96.16
    },
    {
      "name": "Bayamon",
      "totalClients": 216496,
      "totalClientsWithoutService": 88,
      "totalClientsWithService": 216408,
      "totalClientsAffectedByPlannedOutage": 0,
      "percentageClientsWithoutService": 0.04,
      "percentageClientsWithService": 99.96
    },
    {
      "name": "San Juan",
      "totalClients": 253068,
      "totalClientsWithoutService": 102,
      "totalClientsWithService": 252966,
      "totalClientsAffectedByPlannedOutage": 0,
      "percentageClientsWithoutService": 0.04,
      "percentageClientsWithService": 99.96
    },
    {
      "name": "Carolina",
      "totalClients": 141663,
      "totalClientsWithoutService": 270,
      "totalClientsWithService": 141393,
      "totalClientsAffectedByPlannedOutage": 0,
      "percentageClientsWithoutService": 0.19,
      "percentageClientsWithService": 99.81
    },
    {
      "name": "Caguas",
      "totalClients": 250514,
      "totalClientsWithoutService": 8480,
      "totalClientsWithService": 242034,
      "totalClientsAffectedByPlannedOutage": 0,
      "percentageClientsWithoutService": 3.39,
      "percentageClientsWithService": 96.61
    },
    {
      "name": "Ponce",
      "totalClients": 212508,
      "totalClientsWithoutService": 21,
      "totalClientsWithService": 212487,
      "totalClientsAffectedByPlannedOutage": 0,
      "percentageClientsWithoutService": 0.01,
      "percentageClientsWithService": 99.99
    }
  ],
  "totals": {
    "totalClientsWithoutService": 24172,
    "totalClients": 1468223,
    "totalClientsWithService": 1444051,
    "totalPercentageWithoutService": 1.65,
    "totalClientsAffectedByPlannedOutage": 13691,
    "totalPercentageWithService": 98.35
  },
  "timestamp": "02/03/2024 10:15 AM"
}
