{
  "regions": [
    {
      "name": "Arecibo",
      "totalClients": 177369,
      "totalClientsWithoutService": 1655,
      "totalClientsWithService": 175714,
      "percentageClientsWithoutService": 0.93,
      "percentageClientsWithService": 99.07
    },
    {
      "name": "Bayamon",
      "totalClients": 216496,
      "totalClientsWithoutService": 3742,
      "totalClientsWithService": 212754,
      "percentageClientsWithoutService": 1.73,
      "percentageClientsWithService": 98.27
    },
    {
      "name": "Carolina",
      "totalClients": 141663,
      "totalClientsWithoutService": 171,
      "totalClientsWithService": 141492,
      "percentageClientsWithoutService": 0.12,
      "percentageClientsWithService": 99.88
    },
    {
      "name": "Caguas",
      "totalClients": 250514,
      "totalClientsWithoutService": 249,
      "totalClientsWithService": 250265,
      "percentageClientsWithoutService": 0.1,
      "percentageClientsWithService": 99.9
    },
    {
      "name": "Mayaguez",
      "totalClients": 216605,
      "totalClientsWithoutService": 68,
      "totalClientsWithService": 216537,
      "percentageClientsWithoutService": 0.03,
      "percentageClientsWithService": 99.97
    },
    {
      "name": "Ponce",
      "totalClients": 212508,
      "totalClientsWithoutService": 4179,
      "totalClientsWithService": 208329,
      "percentageClientsWithoutService": 1.97,
      "percentageClientsWithService": 98.03
    },
    {
      "name": "San Juan",
      "totalClients": 253068,
      "totalClientsWithoutService": 2743,
      "totalClientsWithService": 250325,
      "percentageClientsWithoutService": 1.08,
      "percentageClientsWithService": 98.92
    }
  ],
  "totals": {
    "totalClientsWithoutService": 12807,
    "totalClients": 1468223,
    "totalClientsWithService": 1455416,
    "totalPercentageWithoutService": 0.87,
    "totalPercentageWithService": 99.13
  },
  "timestamp": "10/28/2023 09:15 AM"
}
