{
  "regions": [
    {
      "name": "Arecibo",
      "totalClients": 177369,
      "totalClientsWithoutService": 1230,
      "totalClientsWithService": 176139,
      "totalClientsAffectedByPlannedOutage": 15,
      "percentageClientsWithoutService": 0.69,
      "percentageClientsWithService": 99.31
    },
    {
      "name": "Bayamon",
      "totalClients": 216496,
      "totalClientsWithoutService": 107,
      "totalClientsWithService": 216389,
      "totalClientsAffectedByPlannedOutage": 0,
      "percentageClientsWithoutService": 0.05,
      "percentageClientsWithService": 99.95
    },
    {
      "name": "Mayaguez",
      "totalClients": 216605,
      "totalClientsWithoutService": 215,
      "totalClientsWithService": 216390,
      "totalClientsAffectedByPlannedOutage": 159,
      "percentageClientsWithoutService": 0.1,
      "percentageClientsWithService": 99.9
    },
    {
      "name": "San Juan",
      "totalClients": 253068,
      "totalClientsWithoutService": 3125,
      "totalClientsWithService": 249943,
      "totalClientsAffectedByPlannedOutage": 3066,
      "percentageClientsWithoutService": 1.23,
      "percentageClientsWithService": 98.77
    },
    {
      "name": "Carolina",
      "totalClients": 141663,
      "totalClientsWithoutService": 23,
      "totalClientsWithService": 141640,
      "totalClientsAffectedByPlannedOutage": 0,
      "percentageClientsWithoutService": 0.02,
      "percentageClientsWithService": 99.98
    },
    {
      "name": "Caguas",
      "totalClients": 250514,
      "totalClientsWithoutService": 277,
      "totalClientsWithService": 250237,
      "totalClientsAffectedByPlannedOutage": 209,
      "percentageClientsWithoutService": 0.11,
      "percentageClientsWithService": 99.89
    },
    {
      "name": "Ponce",
      "totalClients": 212508,
      "totalClientsWithoutService": 1503,
      "totalClientsWithService": 211005,
      "totalClientsAffectedByPlannedOutage": 1501,
      "percentageClientsWithoutService": 0.71,
      "percentageClientsWithService": 99.29
    }
  ],
  "totals": {
    "totalClientsWithoutService": 6480,
    "totalClients": 1468223,
    "totalClientsWithService": 1461743,
    "totalPercentageWithoutService": 0.44,
    "totalClientsAffectedByPlannedOutage": 4950,
    "totalPercentageWithService": 99.56
  },
  "timestamp": "02/01/2024 04:35 PM"
}
