{
  "regions": [
    {
      "name": "Arecibo",
      "totalClients": 177369,
      "totalClientsWithoutService": 164,
      "totalClientsWithService": 177205,
      "percentageClientsWithoutService": 0.09,
      "percentageClientsWithService": 99.91
    },
    {
      "name": "Bayamon",
      "totalClients": 216496,
      "totalClientsWithoutService": 41,
      "totalClientsWithService": 216455,
      "percentageClientsWithoutService": 0.02,
      "percentageClientsWithService": 99.98
    },
    {
      "name": "Carolina",
      "totalClients": 141663,
      "totalClientsWithoutService": 248,
      "totalClientsWithService": 141415,
      "percentageClientsWithoutService": 0.18,
      "percentageClientsWithService": 99.82
    },
    {
      "name": "Caguas",
      "totalClients": 250514,
      "totalClientsWithoutService": 57,
      "totalClientsWithService": 250457,
      "percentageClientsWithoutService": 0.02,
      "percentageClientsWithService": 99.98
    },
    {
      "name": "Mayaguez",
      "totalClients": 216605,
      "totalClientsWithoutService": 47,
      "totalClientsWithService": 216558,
      "percentageClientsWithoutService": 0.02,
      "percentageClientsWithService": 99.98
    },
    {
      "name": "Ponce",
      "totalClients": 212508,
      "totalClientsWithoutService": 627,
      "totalClientsWithService": 211881,
      "percentageClientsWithoutService": 0.3,
      "percentageClientsWithService": 99.7
    },
    {
      "name": "San Juan",
      "totalClients": 253068,
      "totalClientsWithoutService": 268,
      "totalClientsWithService": 252800,
      "percentageClientsWithoutService": 0.11,
      "percentageClientsWithService": 99.89
    }
  ],
  "totals": {
    "totalClientsWithoutService": 1452,
    "totalClients": 1468223,
    "totalClientsWithService": 1466771,
    "totalPercentageWithoutService": 0.1,
    "totalPercentageWithService": 99.9
  },
  "timestamp": "01/16/2024 10:50 AM"
}
