{
  "regions": [
    {
      "name": "Arecibo",
      "totalClients": 177369,
      "totalClientsWithoutService": 916,
      "totalClientsWithService": 176453,
      "percentageClientsWithoutService": 0.52,
      "percentageClientsWithService": 99.48
    },
    {
      "name": "Bayamon",
      "totalClients": 216496,
      "totalClientsWithoutService": 4031,
      "totalClientsWithService": 212465,
      "percentageClientsWithoutService": 1.86,
      "percentageClientsWithService": 98.14
    },
    {
      "name": "Carolina",
      "totalClients": 141663,
      "totalClientsWithoutService": 1949,
      "totalClientsWithService": 139714,
      "percentageClientsWithoutService": 1.38,
      "percentageClientsWithService": 98.62
    },
    {
      "name": "Caguas",
      "totalClients": 250514,
      "totalClientsWithoutService": 5452,
      "totalClientsWithService": 245062,
      "percentageClientsWithoutService": 2.18,
      "percentageClientsWithService": 97.82
    },
    {
      "name": "Mayaguez",
      "totalClients": 216605,
      "totalClientsWithoutService": 336,
      "totalClientsWithService": 216269,
      "percentageClientsWithoutService": 0.16,
      "percentageClientsWithService": 99.84
    },
    {
      "name": "Ponce",
      "totalClients": 212508,
      "totalClientsWithoutService": 255,
      "totalClientsWithService": 212253,
      "percentageClientsWithoutService": 0.12,
      "percentageClientsWithService": 99.88
    },
    {
      "name": "San Juan",
      "totalClients": 253068,
      "totalClientsWithoutService": 2860,
      "totalClientsWithService": 250208,
      "percentageClientsWithoutService": 1.13,
      "percentageClientsWithService": 98.87
    }
  ],
  "totals": {
    "totalClientsWithoutService": 15799,
    "totalClients": 1468223,
    "totalClientsWithService": 1452424,
    "totalPercentageWithoutService": 1.08,
    "totalPercentageWithService": 98.92
  },
  "timestamp": "12/10/2023 11:20 AM"
}
