{
  "regions": [
    {
      "name": "Arecibo",
      "totalClients": 177369,
      "totalClientsWithoutService": 2,
      "totalClientsWithService": 177367,
      "totalClientsAffectedByPlannedOutage": 0,
      "percentageClientsWithoutService": 0,
      "percentageClientsWithService": 100
    },
    {
      "name": "Bayamon",
      "totalClients": 216496,
      "totalClientsWithoutService": 7,
      "totalClientsWithService": 216489,
      "totalClientsAffectedByPlannedOutage": 0,
      "percentageClientsWithoutService": 0,
      "percentageClientsWithService": 100
    },
    {
      "name": "Mayaguez",
      "totalClients": 216605,
      "totalClientsWithoutService": 1397,
      "totalClientsWithService": 215208,
      "totalClientsAffectedByPlannedOutage": 0,
      "percentageClientsWithoutService": 0.64,
      "percentageClientsWithService": 99.36
    },
    {
      "name": "San Juan",
      "totalClients": 253068,
      "totalClientsWithoutService": 155,
      "totalClientsWithService": 252913,
      "totalClientsAffectedByPlannedOutage": 0,
      "percentageClientsWithoutService": 0.06,
      "percentageClientsWithService": 99.94
    },
    {
      "name": "Carolina",
      "totalClients": 141663,
      "totalClientsWithoutService": 1,
      "totalClientsWithService": 141662,
      "totalClientsAffectedByPlannedOutage": 0,
      "percentageClientsWithoutService": 0,
      "percentageClientsWithService": 100
    },
    {
      "name": "Caguas",
      "totalClients": 250514,
      "totalClientsWithoutService": 17,
      "totalClientsWithService": 250497,
      "totalClientsAffectedByPlannedOutage": 0,
      "percentageClientsWithoutService": 0.01,
      "percentageClientsWithService": 99.99
    },
    {
      "name": "Ponce",
      "totalClients": 212508,
      "totalClientsWithoutService": 13,
      "totalClientsWithService": 212495,
      "totalClientsAffectedByPlannedOutage": 0,
      "percentageClientsWithoutService": 0.01,
      "percentageClientsWithService": 99.99
    }
  ],
  "totals": {
    "totalClientsWithoutService": 1592,
    "totalClients": 1468223,
    "totalClientsWithService": 1466631,
    "totalPercentageWithoutService": 0.11,
    "totalClientsAffectedByPlannedOutage": 0,
    "totalPercentageWithService": 99.89
  },
  "timestamp": "04/07/2024 02:45 PM"
}
